Workbook

Sheet Инструкция
A1: Домашняя выпечка — расчёт
A3: Как пользоваться
A4: 1. Синие цифры на жёлтом фоне — то, что вы меняете сами: цены продуктов, рецептуры, цены продажи, объёмы продаж.
A5: 2. Чёрные цифры считаются формулами — их не трогать.
A6: 3. Зелёные цифры подтягиваются с других листов.
A7: 4. Поменяли цену масла на листе «Цены продуктов» — себестоимость, маржа и прибыль пересчитаются сами.
A8: 5. Лист «Учёт продаж» — журнал: каждая продажа одной строкой. Строка 5 — пример, её можно удалить.
A10: Листы
A11: Цены продуктов — закупочные цены (Алматинская обл., октябрь 2026, ориентир)
A12: Себестоимость — рецептуры на одну партию и стоимость одной штуки
A13: Цены и маржа — цена набора, сколько остаётся с каждой продажи
A14: Сценарии — 3 варианта спроса: выручка, прибыль за месяц, часы работы, окупаемость
... A16: Учёт продаж — журнал продаж с итогами

Sheet Цены продуктов
A1: Цены закупки
A2: Синие ячейки — меняйте на свои цены из магазина. Цена за единицу считается сама.
A4: Продукт | B4: Упаковка | C4: Цена упаковки, тг | D4: Сколько в упаковке | E4: Единица | F4: Цена за единицу, тг | G4: Откуда цена
A5: Мука высший сорт | B5: пакет 2 кг | C5: 800 | D5: 2 | E5: кг | F5: =C5/D5 -> 400 | G5: Магазины Алматы, 2026 (~389–499 тг/кг)
A6: Сахар | B6: пакет 1 кг | C6: 500 | D6: 1 | E6: кг | F6: =C6/D6 -> 500 | G6: Оценка, проверить в магазине
A7: Яйца С1 | B7: десяток | C7: 650 | D7: 10 | E7: шт | F7: =C7/D7 -> 65 | G7: Алматы 2026: 545–590 тг + инфляция
A8: Масло сливочное 72,5% | B8: пачка 180 г | C8: 650 | D8: 0.18 | E8: кг | F8: =C8/D8 -> 3611.1111 | G8: Алматы 2026: развес 2510–2930 тг/кг; пачка дороже
A9: Маргарин сливочный | B9: пачка 250 г | C9: 400 | D9: 0.25 | E9: кг | F9: =C9/D9 -> 1600 | G9: Оценка, проверить в магазине
A10: Сгущёнка варёная | B10: банка 380 г | C10: 750 | D10: 1 | E10: банка | F10: =C10/D10 -> 750 | G10: Оценка, проверить в магазине
A11: Яблоки | B11: кг | C11: 350 | D11: 1 | E11: кг | F11: =C11/D11 -> 350 | G11: Цена в домовом чате: 300–400 тг/кг
A12: Разрыхлитель, ванилин, сода, корица | B12: на одну партию | C12: 60 | D12: 1 | E12: партия | F12: =C12/D12 -> 60 | G12: Оценка
A13: Бумага для выпечки | B13: лист | C13: 30 | D13: 1 | E13: шт | F13: =C13/D13 -> 30 | G13: Оценка
A14: Коробка для пирога 26 см | B14: шт | C14: 350 | D14: 1 | E14: шт | F14: =C14/D14 -> 350 | G14: Оценка, оптом дешевле
A15: Крафт-коробка с окном | B15: шт | C15: 150 | D15: 1 | E15: шт | F15: =C15/D15 -> 150 | G15: Оценка, оптом дешевле
A16: Наклейка с составом и датой | B16: шт | C16: 20 | D16: 1 | E16: шт | F16: =C16/D16 -> 20 | G16: Оценка

Sheet Себестоимость
A1: Себестоимость: рецептуры на одну партию
A2: Количество (синие) можно менять. Название продукта должно совпадать с листом «Цены продуктов».
A3: Масло сливочное 72,5% в орешках и трубочках указано двумя строками: в тесто и в крем.
A4: Орешки со сгущёнкой
A5: Ингредиент | B5: Количество | C5: Единица | D5: Цена за единицу, тг | E5: Стоимость, тг
A6: Мука высший сорт | B6: 0.45 | C6: =INDEX('Цены продуктов'!$E$5:$E$16,MATCH(A6,'Цены продуктов'!$A$5:$A$16,0)) -> кг | D6: =INDEX('Цены продуктов'!$F$5:$F$16,MATCH(A6,'Цены продуктов'!$A$5:$A$16,0)) -> 400 | E6: =B6*D6 -> 180
A7: Масло сливочное 72,5% | B7: 0.2 | C7: =INDEX('Цены продуктов'!$E$5:$E$16,MATCH(A7,'Цены продуктов'!$A$5:$A$16,0)) -> кг | D7: =INDEX('Цены продуктов'!$F$5:$F$16,MATCH(A7,'Цены продуктов'!$A$5:$A$16,0)) -> 3611.1111 | E7: =B7*D7 -> 722.22222
A8: Яйца С1 | B8: 2 | C8: =INDEX('Цены продуктов'!$E$5:$E$16,MATCH(A8,'Цены продуктов'!$A$5:$A$16,0)) -> шт | D8: =INDEX('Цены продуктов'!$F$5:$F$16,MATCH(A8,'Цены продуктов'!$A$5:$A$16,0)) -> 65 | E8: =B8*D8 -> 130
A9: Сахар | B9: 0.15 | C9: =INDEX('Цены продуктов'!$E$5:$E$16,MATCH(A9,'Цены продуктов'!$A$5:$A$16,0)) -> кг | D9: =INDEX('Цены продуктов'!$F$5:$F$16,MATCH(A9,'Цены продуктов'!$A$5:$A$16,0)) -> 500 | E9: =B9*D9 -> 75
A10: Разрыхлитель, ванилин, сода, корица | B10: 1 | C10: =INDEX('Цены продуктов'!$E$5:$E$16,MATCH(A10,'Цены продуктов'!$A$5:$A$16,0)) -> партия | D10: =INDEX('Цены продуктов'!$F$5:$F$16,MATCH(A10,'Цены продуктов'!$A$5:$A$16,0)) -> 60 | E10: =B10*D10 -> 60
A11: Сгущёнка варёная | B11: 1.5 | C11: =INDEX('Цены продуктов'!$E$5:$E$16,MATCH(A11,'Цены продуктов'!$A$5:$A$16,0)) -> банка | D11: =INDEX('Цены продуктов'!$F$5:$F$16,MATCH(A11,'Цены продуктов'!$A$5:$A$16,0)) -> 750 | E11: =B11*D11 -> 1125
A12: Масло сливочное 72,5% | B12: 0.05 | C12: =INDEX('Цены продуктов'!$E$5:$E$16,MATCH(A12,'Цены продуктов'!$A$5:$A$16,0)) -> кг | D12: =INDEX('Цены продуктов'!$F$5:$F$16,MATCH(A12,'Цены продуктов'!$A$5:$A$16,0)) -> 3611.1111 | E12: =B12*D12 -> 180.55556
A13: Итого на партию | E13: =SUM(E6:E12) -> 2472.7778
A14: Выход партии (орешков (100 половинок)) | B14: 50
A15: Себестоимость 1 шт (без упаковки) | E15: =E13/B14 -> 49.455556
A17: Вафельные трубочки со сгущёнкой
A18: Ингредиент | B18: Количество | C18: Единица | D18: Цена за единицу, тг | E18: Стоимость, тг
A19: Мука высший сорт | B19: 0.25 | C19: =INDEX('Цены продуктов'!$E$5:$E$16,MATCH(A19,'Цены продуктов'!$A$5:$A$16,0)) -> кг | D19: =INDEX('Цены продуктов'!$F$5:$F$16,MATCH(A19,'Цены продуктов'!$A$5:$A$16,0)) -> 400 | E19: =B19*D19 -> 100
A20: Маргарин сливочный | B20: 0.2 | C20: =INDEX('Цены продуктов'!$E$5:$E$16,MATCH(A20,'Цены продуктов'!$A$5:$A$16,0)) -> кг | D20: =INDEX('Цены продуктов'!$F$5:$F$16,MATCH(A20,'Цены продуктов'!$A$5:$A$16,0)) -> 1600 | E20: =B20*D20 -> 320
A21: Яйца С1 | B21: 5 | C21: =INDEX('Цены продуктов'!$E$5:$E$16,MATCH(A21,'Цены продуктов'!$A$5:$A$16,0)) -> шт | D21: =INDEX('Цены продуктов'!$F$5:$F$16,MATCH(A21,'Цены продуктов'!$A$5:$A$16,0)) -> 65 | E21: =B21*D21 -> 325
A22: Сахар | B22: 0.2 | C22: =INDEX('Цены продуктов'!$E$5:$E$16,MATCH(A22,'Цены продуктов'!$A$5:$A$16,0)) -> кг | D22: =INDEX('Цены продуктов'!$F$5:$F$16,MATCH(A22,'Цены продуктов'!$A$5:$A$16,0)) -> 500 | E22: =B22*D22 -> 100
A23: Разрыхлитель, ванилин, сода, корица | B23: 1 | C23: =INDEX('Цены продуктов'!$E$5:$E$16,MATCH(A23,'Цены продуктов'!$A$5:$A$16,0)) -> партия | D23: =INDEX('Цены продуктов'!$F$5:$F$16,MATCH(A23,'Цены продуктов'!$A$5:$A$16,0)) -> 60 | E23: =B23*D23 -> 60
A24: Сгущёнка варёная | B24: 1.5 | C24: =INDEX('Цены продуктов'!$E$5:$E$16,MATCH(A24,'Цены продуктов'!$A$5:$A$16,0)) -> банка | D24: =INDEX('Цены продуктов'!$F$5:$F$16,MATCH(A24,'Цены продуктов'!$A$5:$A$16,0)) -> 750 | E24: =B24*D24 -> 1125
A25: Масло сливочное 72,5% | B25: 0.05 | C25: =INDEX('Цены продуктов'!$E$5:$E$16,MATCH(A25,'Цены продуктов'!$A$5:$A$16,0)) -> кг | D25: =INDEX('Цены продуктов'!$F$5:$F$16,MATCH(A25,'Цены продуктов'!$A$5:$A$16,0)) -> 3611.1111 | E25: =B25*D25 -> 180.55556
A26: Итого на партию | E26: =SUM(E19:E25) -> 2210.5556
A27: Выход партии (трубочек) | B27: 30
A28: Себестоимость 1 шт (без упаковки) | E28: =E26/B27 -> 73.685185
A30: Шарлотка (форма 26 см)
A31: Ингредиент | B31: Количество | C31: Единица | D31: Цена за единицу, тг | E31: Стоимость, тг
A32: Яйца С1 | B32: 5 | C32: =INDEX('Цены продуктов'!$E$5:$E$16,MATCH(A32,'Цены продуктов'!$A$5:$A$16,0)) -> шт | D32: =INDEX('Цены продуктов'!$F$5:$F$16,MATCH(A32,'Цены продуктов'!$A$5:$A$16,0)) -> 65 | E32: =B32*D32 -> 325
A33: Сахар | B33: 0.2 | C33: =INDEX('Цены продуктов'!$E$5:$E$16,MATCH(A33,'Цены продуктов'!$A$5:$A$16,0)) -> кг | D33: =INDEX('Цены продуктов'!$F$5:$F$16,MATCH(A33,'Цены продуктов'!$A$5:$A$16,0)) -> 500 | E33: =B33*D33 -> 100
A34: Мука высший сорт | B34: 0.2 | C34: =INDEX('Цены продуктов'!$E$5:$E$16,MATCH(A34,'Цены продуктов'!$A$5:$A$16,0)) -> кг | D34: =INDEX('Цены продуктов'!$F$5:$F$16,MATCH(A34,'Цены продуктов'!$A$5:$A$16,0)) -> 400 | E34: =B34*D34 -> 80
A35: Яблоки | B35: 0.8 | C35: =INDEX('Цены продуктов'!$E$5:$E$16,MATCH(A35,'Цены продуктов'!$A$5:$A$16,0)) -> кг | D35: =INDEX('Цены продуктов'!$F$5:$F$16,MATCH(A35,'Цены продуктов'!$A$5:$A$16,0)) -> 350 | E35: =B35*D35 -> 280
A36: Масло сливочное 72,5% | B36: 0.01 | C36: =INDEX('Цены продуктов'!$E$5:$E$16,MATCH(A36,'Цены продуктов'!$A$5:$A$16,0)) -> кг | D36: =INDEX('Цены продуктов'!$F$5:$F$16,MATCH(A36,'Цены продуктов'!$A$5:$A$16,0)) -> 3611.1111 | E36: =B36*D36 -> 36.111111
A37: Разрыхлитель, ванилин, сода, корица | B37: 0.5 | C37: =INDEX('Цены продуктов'!$E$5:$E$16,MATCH(A37,'Цены продуктов'!$A$5:$A$16,0)) -> партия | D37: =INDEX('Цены продуктов'!$F$5:$F$16,MATCH(A37,'Цены продуктов'!$A$5:$A$16,0)) -> 60 | E37: =B37*D37 -> 30
A38: Бумага для выпечки | B38: 1 | C38: =INDEX('Цены продуктов'!$E$5:$E$16,MATCH(A38,'Цены продуктов'!$A$5:$A$16,0)) -> шт | D38: =INDEX('Цены продуктов'!$F$5:$F$16,MATCH(A38,'Цены продуктов'!$A$5:$A$16,0)) -> 30 | E38: =B38*D38 -> 30
A39: Итого на партию | E39: =SUM(E32:E38) -> 881.11111
A40: Выход партии (пирог ~1,2 кг) | B40: 1
A41: Себестоимость 1 шт (без упаковки) | E41: =E39/B40 -> 881.11111

Sheet Цены и маржа
A1: Цены продажи и маржа с одного набора
A3: Товар (набор) | B3: Штук в наборе | C3: Себестоимость 1 шт, тг | D3: Продукты на набор, тг | E3: Упаковка | F3: Упаковка + наклейка, тг | G3: Полная себестоимость набора, тг | H3: Цена продажи, тг | I3: Остаётся с продажи, тг | J3: Маржа, % | K3: Часов на набор (с доставкой) | L3: Заработок за 1 час, тг
A4: Орешки со сгущёнкой, 12 шт | B4: 12 | C4: =Себестоимость!$E$15 -> 49.455556 | D4: =B4*C4 -> 593.46667 | E4: Крафт-коробка с окном | F4: =INDEX('Цены продуктов'!$F$5:$F$16,MATCH(E4,'Цены продуктов'!$A$5:$A$16,0))+INDEX('Цены продуктов'!$F$5:$F$16,MATCH("Наклейка с составом и датой",'Цены продуктов'!$A$5:$A$16,0)) -> 170 | G4: =D4+F4 -> 763.46667 | H4: 1500 | I4: =H4-G4 -> 736.53333 | J4: =IF(H4=0,0,I4/H4) -> 0.49102222 | K4: =Сценарии!$B$35+Сценарии!$B$39 -> 0.9 | L4: =IF(K4=0,0,I4/K4) -> 818.37037
A5: Вафельные трубочки, 10 шт | B5: 10 | C5: =Себестоимость!$E$28 -> 73.685185 | D5: =B5*C5 -> 736.85185 | E5: Крафт-коробка с окном | F5: =INDEX('Цены продуктов'!$F$5:$F$16,MATCH(E5,'Цены продуктов'!$A$5:$A$16,0))+INDEX('Цены продуктов'!$F$5:$F$16,MATCH("Наклейка с составом и датой",'Цены продуктов'!$A$5:$A$16,0)) -> 170 | G5: =D5+F5 -> 906.85185 | H5: 1800 | I5: =H5-G5 -> 893.14815 | J5: =IF(H5=0,0,I5/H5) -> 0.49619342 | K5: =Сценарии!$B$36+Сценарии!$B$39 -> 1 | L5: =IF(K5=0,0,I5/K5) -> 893.14815
A6: Шарлотка целая, 26 см | B6: 1 | C6: =Себестоимость!$E$41 -> 881.11111 | D6: =B6*C6 -> 881.11111 | E6: Коробка для пирога 26 см | F6: =INDEX('Цены продуктов'!$F$5:$F$16,MATCH(E6,'Цены продуктов'!$A$5:$A$16,0))+INDEX('Цены продуктов'!$F$5:$F$16,MATCH("Наклейка с составом и датой",'Цены продуктов'!$A$5:$A$16,0)) -> 370 | G6: =D6+F6 -> 1251.1111 | H6: 3000 | I6: =H6-G6 -> 1748.8889 | J6: =IF(H6=0,0,I6/H6) -> 0.58296296 | K6: =Сценарии!$B$37+Сценарии!$B$39 -> 0.55 | L6: =IF(K6=0,0,I6/K6) -> 3179.798
A8: Цены продажи — гипотеза для старта. Ориентир чата: кимчи 2000 тг за 1 л, яблоки 300–400 тг/кг (данные пользователя).
A9: Если маржа ниже 40% — поднимите цену или замените часть сливочного масла маргарином на листе «Себестоимость».

Sheet Сценарии
A1: Сценарии спроса: сколько можно заработать
A2: Объёмы продаж в неделю (синие) — меняйте по факту. Остальное считается.
A4: Показатель | B4: Осторожный | C4: Базовый | D4: Удачный | E4: Пояснение
A5: Орешки, наборов в неделю | B5: 3 | C5: 6 | D5: 10 | E5: Осторожный ≈ 5% домов покупают раз в неделю; базовый ≈ 10%; удачный ≈ 16% (154 дома)
A6: Трубочки, наборов в неделю | B6: 2 | C6: 4 | D6: 7
A7: Шарлотка, пирогов в неделю | B7: 3 | C7: 5 | D7: 8
A8: Продаж в неделю, шт | B8: =SUM(B5:B7) -> 8 | C8: =SUM(C5:C7) -> 15 | D8: =SUM(D5:D7) -> 25
A9: Доля домов посёлка | B9: =B8/$B$30 -> 0.051948052 | C9: =C8/$B$30 -> 0.097402597 | D9: =D8/$B$30 -> 0.16233766 | E9: Сколько домов из 154 покупают раз в неделю
A11: Выручка в неделю, тг | B11: =B5*'Цены и маржа'!$H$4+B6*'Цены и маржа'!$H$5+B7*'Цены и маржа'!$H$6 -> 17100 | C11: =C5*'Цены и маржа'!$H$4+C6*'Цены и маржа'!$H$5+C7*'Цены и маржа'!$H$6 -> 31200 | D11: =D5*'Цены и маржа'!$H$4+D6*'Цены и маржа'!$H$5+D7*'Цены и маржа'!$H$6 -> 51600
A12: Затраты на продукты и упаковку в неделю, тг | B12: =B5*'Цены и маржа'!$G$4+B6*'Цены и маржа'!$G$5+B7*'Цены и маржа'!$G$6 -> 7857.437 | C12: =C5*'Цены и маржа'!$G$4+C6*'Цены и маржа'!$G$5+C7*'Цены и маржа'!$G$6 -> 14463.763 | D12: =D5*'Цены и маржа'!$G$4+D6*'Цены и маржа'!$G$5+D7*'Цены и маржа'!$G$6 -> 23991.519
A13: Валовая прибыль в неделю, тг | B13: =B11-B12 -> 9242.563 | C13: =C11-C12 -> 16736.237 | D13: =D11-D12 -> 27608.481
A15: Выручка в месяц, тг | B15: =B11*$B$31 -> 73530 | C15: =C11*$B$31 -> 134160 | D15: =D11*$B$31 -> 221880
A16: Продукты и упаковка в месяц, тг | B16: =B12*$B$31 -> 33786.979 | C16: =C12*$B$31 -> 62194.181 | D16: =D12*$B$31 -> 103163.53
A17: Свет и газ, тг в месяц | B17: =$B$32 -> 4000 | C17: =$B$32 -> 4000 | D17: =$B$32 -> 4000
A18: Пробники, брак, списания, тг | B18: =B15*$B$33 -> 3676.5 | C18: =C15*$B$33 -> 6708 | D18: =D15*$B$33 -> 11094
A19: Налог самозанятого, тг | B19: =B15*$B$34 -> 2941.2 | C19: =C15*$B$34 -> 5366.4 | D19: =D15*$B$34 -> 8875.2
A20: Чистая прибыль в месяц, тг | B20: =B15-B16-B17-B18-B19 -> 29125.321 | C20: =C15-C16-C17-C18-C19 -> 55891.419 | D20: =D15-D16-D17-D18-D19 -> 94747.27
A22: Часов работы в неделю | B22: =B5*$B$35+B6*$B$36+B7*$B$37+$B$38+B8*$B$39 -> 7.85 | C22: =C5*$B$35+C6*$B$36+C7*$B$37+$B$38+C8*$B$39 -> 13.65 | D22: =D5*$B$35+D6*$B$36+D7*$B$37+$B$38+D8*$B$39 -> 21.9 | E22: Выпечка + упаковка + закупка + чат и доставка
A23: Часов в день при 5 рабочих днях | B23: =B22/5 -> 1.57 | C23: =C22/5 -> 2.73 | D23: =D22/5 -> 4.38
A24: Заработок за 1 час работы, тг | B24: =IF(B22=0,0,B20/(B22*$B$31)) -> 862.84464 | C24: =IF(C22=0,0,C20/(C22*$B$31)) -> 952.23476 | D24: =IF(D22=0,0,D20/(D22*$B$31)) -> 1006.1301
A25: Окупаемость стартовых вложений, недель | B25: =IF(B20<=0,"не окупится",Старт!$C$12/(B20/$B$31)) -> 9.448823 | C25: =IF(C20<=0,"не окупится",Старт!$C$12/(C20/$B$31)) -> 4.9238327 | D25: =IF(D20<=0,"не окупится",Старт!$C$12/(D20/$B$31)) -> 2.9045692
A29: Допущения
A30: Домов в посёлке | B30: 154 | E30: Данные пользователя
A31: Недель в месяце | B31: 4.3 | E31: Среднее
A32: Свет и газ на выпечку, тг в месяц | B32: 4000 | E32: Оценка: ~25 кВт·ч в месяц на орешницу и вафельницу + духовка
A33: Пробники и брак, доля выручки | B33: 0.05 | E33: Первые месяцы — бесплатные пробы для соседей
A34: Налог самозанятого, доля выручки | B34: 0.04 | E34: Режим самозанятых с 01.01.2026: 4% с дохода. Проверить, входит ли выпечка в перечень видов деятельности
A35: Часов на 1 набор орешков (12 шт) | B35: 0.75 | E35: Партия 50 шт ≈ 3 ч: тесто, выпекание, начинка
A36: Часов на 1 набор трубочек (10 шт) | B36: 0.85 | E36: Партия 30 шт ≈ 2,5 ч
A37: Часов на 1 шарлотку | B37: 0.4 | E37: 2 пирога в духовке одновременно
A38: Часов в неделю на закупку | B38: 1.5 | E38: Одна поездка в магазин
A39: Часов на 1 продажу: переписка и доставка | B39: 0.15 | E39: По посёлку пешком или на машине

Sheet Старт
A1: Стартовые вложения
A3: Что купить | B3: Количество | C3: Цена, тг | D3: Сумма, тг | E3: Комментарий
A4: Орешница электрическая (16 половинок за цикл) | B4: 1 | C4: 15000 | D4: =B4*C4 -> 15000 | E4: Антипригарное покрытие, терморегулятор. Электро удобнее газовой: ровный нагрев, не нужно переворачивать
A5: Вафельница электрическая для тонких вафель | B5: 1 | C5: 13000 | D5: =B5*C5 -> 13000 | E5: Тонкие вафли «как в детстве», их можно свернуть в трубочку
A6: Разъёмная форма 26 см | B6: 2 | C6: 3500 | D6: =B6*C6 -> 7000 | E6: Две формы — два пирога за одну закладку в духовку
A7: Кухонные весы | B7: 1 | C7: 5000 | D7: =B7*C7 -> 5000 | E7: Точная рецептура = стабильный вкус и себестоимость
A8: Конусы для трубочек, кондитерский мешок, лопатки | B8: 1 | C8: 4000 | D8: =B8*C8 -> 4000
A9: Упаковка на старт: коробки и наклейки | B9: 1 | C9: 10000 | D9: =B9*C9 -> 10000 | E9: ~40 крафт-коробок + 10 коробок для пирогов + наклейки
A10: Пробные партии (отработка рецептов, дегустация соседям) | B10: 1 | C10: 10000 | D10: =B10*C10 -> 10000 | E10: 2–3 пробные партии каждого вида
A12: Итого стартовых вложений | C12: =SUM(D4:D10) -> 64000
A13: Миксер, духовка, посуда — считаем, что уже есть. Цены техники — ориентир по Kaspi/маркетплейсам, проверить перед покупкой.

Sheet Учёт продаж
A1: Журнал продаж
A2: Каждая продажа — одна строка. Товар выбирайте из списка, цена подставится сама. Строка 5 — пример.
A4: Дата | B4: Дом / имя | C4: Товар | D4: Количество | E4: Цена, тг | F4: Сумма, тг | G4: Оплата | H4: Доставка | I4: Отзыв | K4: Итоги
A5: 46312 | B5: Дом 42, Айгерим | C5: Шарлотка целая, 26 см | D5: 1 | E5: =IF(C5="","",INDEX('Цены и маржа'!$H$4:$H$6,MATCH(C5,'Цены и маржа'!$A$4:$A$6,0))) -> 3000 | F5: =IF(C5="","",D5*E5) -> 3000 | G5: Kaspi | H5: Доставка | I5: Просила ещё в субботу | K5: Выручка всего, тг | L5: =SUM(F5:F204) -> 3000
E6: =IF(C6="","",INDEX('Цены и маржа'!$H$4:$H$6,MATCH(C6,'Цены и маржа'!$A$4:$A$6,0))) | F6: =IF(C6="","",D6*E6) | K6: Продаж всего | L6: =COUNTA(C5:C204) -> 1
E7: =IF(C7="","",INDEX('Цены и маржа'!$H$4:$H$6,MATCH(C7,'Цены и маржа'!$A$4:$A$6,0))) | F7: =IF(C7="","",D7*E7) | K7: Остаётся с продаж (по марже), тг | L7: =SUMPRODUCT(SUMIF(C5:C204,'Цены и маржа'!$A$4:$A$6,D5:D204)*'Цены и маржа'!$I$4:$I$6) -> 1748.8889
E8: =IF(C8="","",INDEX('Цены и маржа'!$H$4:$H$6,MATCH(C8,'Цены и маржа'!$A$4:$A$6,0))) | F8: =IF(C8="","",D8*E8) | K8: Продано наборов по товарам
E9: =IF(C9="","",INDEX('Цены и маржа'!$H$4:$H$6,MATCH(C9,'Цены и маржа'!$A$4:$A$6,0))) | F9: =IF(C9="","",D9*E9) | K9: ='Цены и маржа'!A4 -> Орешки со сгущёнкой, 12 шт | L9: =SUMIF(C$5:C$204,K9,D$5:D$204) -> 0
E10: =IF(C10="","",INDEX('Цены и маржа'!$H$4:$H$6,MATCH(C10,'Цены и маржа'!$A$4:$A$6,0))) | F10: =IF(C10="","",D10*E10) | K10: ='Цены и маржа'!A5 -> Вафельные трубочки, 10 шт | L10: =SUMIF(C$5:C$204,K10,D$5:D$204) -> 0
E11: =IF(C11="","",INDEX('Цены и маржа'!$H$4:$H$6,MATCH(C11,'Цены и маржа'!$A$4:$A$6,0))) | F11: =IF(C11="","",D11*E11) | K11: ='Цены и маржа'!A6 -> Шарлотка целая, 26 см | L11: =SUMIF(C$5:C$204,K11,D$5:D$204) -> 1
E12: =IF(C12="","",INDEX('Цены и маржа'!$H$4:$H$6,MATCH(C12,'Цены и маржа'!$A$4:$A$6,0))) | F12: =IF(C12="","",D12*E12)
E13: =IF(C13="","",INDEX('Цены и маржа'!$H$4:$H$6,MATCH(C13,'Цены и маржа'!$A$4:$A$6,0))) | F13: =IF(C13="","",D13*E13)
E14: =IF(C14="","",INDEX('Цены и маржа'!$H$4:$H$6,MATCH(C14,'Цены и маржа'!$A$4:$A$6,0))) | F14: =IF(C14="","",D14*E14)
E15: =IF(C15="","",INDEX('Цены и маржа'!$H$4:$H$6,MATCH(C15,'Цены и маржа'!$A$4:$A$6,0))) | F15: =IF(C15="","",D15*E15)
E16: =IF(C16="","",INDEX('Цены и маржа'!$H$4:$H$6,MATCH(C16,'Цены и маржа'!$A$4:$A$6,0))) | F16: =IF(C16="","",D16*E16)
E17: =IF(C17="","",INDEX('Цены и маржа'!$H$4:$H$6,MATCH(C17,'Цены и маржа'!$A$4:$A$6,0))) | F17: =IF(C17="","",D17*E17)
E18: =IF(C18="","",INDEX('Цены и маржа'!$H$4:$H$6,MATCH(C18,'Цены и маржа'!$A$4:$A$6,0))) | F18: =IF(C18="","",D18*E18)
E19: =IF(C19="","",INDEX('Цены и маржа'!$H$4:$H$6,MATCH(C19,'Цены и маржа'!$A$4:$A$6,0))) | F19: =IF(C19="","",D19*E19)
E20: =IF(C20="","",INDEX('Цены и маржа'!$H$4:$H$6,MATCH(C20,'Цены и маржа'!$A$4:$A$6,0))) | F20: =IF(C20="","",D20*E20)
E21: =IF(C21="","",INDEX('Цены и маржа'!$H$4:$H$6,MATCH(C21,'Цены и маржа'!$A$4:$A$6,0))) | F21: =IF(C21="","",D21*E21)
E22: =IF(C22="","",INDEX('Цены и маржа'!$H$4:$H$6,MATCH(C22,'Цены и маржа'!$A$4:$A$6,0))) | F22: =IF(C22="","",D22*E22)
E23: =IF(C23="","",INDEX('Цены и маржа'!$H$4:$H$6,MATCH(C23,'Цены и маржа'!$A$4:$A$6,0))) | F23: =IF(C23="","",D23*E23)
... E204: =IF(C204="","",INDEX('Цены и маржа'!$H$4:$H$6,MATCH(C204,'Цены и маржа'!$A$4:$A$6,0))) | F204: =IF(C204="","",D204*E204)
